{
  "mocks": [
    {
      "title": "mocksDataasdf",
      "author": "twk1122",
      "id": 1
    },
    {
      "title": "444",
      "author": "twk",
      "id": 3
    },
    {
      "title": "444",
      "author": "twk1212",
      "id": 5
    },
    {
      "title": "444",
      "author": "twk",
      "id": 6
    },
    {
      "title": "444",
      "author": "twk",
      "id": 7
    },
    {
      "title": "444",
      "author": "twk",
      "id": 8
    },
    {
      "title": "444",
      "author": "twk",
      "id": 9
    },
    {
      "title": "444",
      "author": "twk",
      "id": 10
    },
    {
      "title": "adsf",
      "author": "adsf",
      "id": 11
    },
    {
      "title": "asdf",
      "author": "sadf",
      "id": 12
    },
    {
      "title": "asdf11222",
      "author": "11",
      "id": 13
    },
    {
      "id": 14
    },
    {
      "id": 15
    },
    {
      "id": 16
    },
    {
      "title": "dsf",
      "author": "asdf",
      "id": 17
    },
    {
      "title": "dsf",
      "author": "asdfasdf",
      "id": 18
    },
    {
      "title": "dsf",
      "author": "asdfasdf",
      "id": 19
    },
    {
      "id": 20
    },
    {
      "id": 21
    },
    {
      "id": 22
    },
    {
      "id": 23
    },
    {
      "id": 24
    },
    {
      "id": 25
    },
    {
      "id": 26
    },
    {
      "id": 28
    },
    {
      "id": 29
    },
    {
      "id": 30
    },
    {
      "title": "asdfsdasdf",
      "author": "asdfsd",
      "id": 31
    },
    {
      "id": 32
    },
    {
      "id": 33
    },
    {
      "id": 34
    },
    {
      "id": 35
    },
    {
      "title": "sdfsdfsdfsdfsd",
      "author": "sdfsdf",
      "id": 36
    },
    {
      "title": "444",
      "author": "twk",
      "id": 37
    },
    {
      "title": "mocksData",
      "author": "twk11",
      "id": 38
    },
    {
      "title": "121222112212121",
      "author": "212112122121",
      "id": 39
    },
    {
      "title": "1212",
      "author": "1221212121",
      "id": 40
    }
  ],
  "posts": [
    {
      "id": 1,
      "title": "json-server",
      "author": "typicode"
    }
  ],
  "comments": [
    {
      "id": 1,
      "body": "some comment",
      "postId": 1
    }
  ],
  "profile": {
    "name": "typicode"
  }
}
